pyasterix/__init__.py
pyasterix/connection.py
pyasterix/cursor.py
pyasterix/exceptions.py
pyasterix/observability.py
pyasterix/pool.py
pyasterix/dataframe/__init__.py
pyasterix/dataframe/attribute.py
pyasterix/dataframe/base.py
pyasterix/dataframe/query.py
pyasterix-0.1.3.dist-info/licenses/LICENSE
pyasterix-0.1.3.dist-info/METADATA
pyasterix-0.1.3.dist-info/WHEEL
pyasterix-0.1.3.dist-info/top_level.txt
pyasterix-0.1.3.dist-info/RECORD
