Metadata-Version: 2.4
Name: pyasterix
Version: 0.1.3
Summary: Python connector for AsterixDB
Author-email: Your Name <you@example.com>
License: MIT License
Project-URL: Homepage, https://github.com/your-org/pyasterix
Project-URL: Documentation, https://github.com/your-org/pyasterix/tree/main/docs
Project-URL: Issues, https://github.com/your-org/pyasterix/issues
Keywords: AsterixDB,SQL++,database,connector,driver
Classifier: Development Status :: 4 - Beta
Classifier: Intended Audience :: Developers
Classifier: License :: OSI Approved :: MIT License
Classifier: Programming Language :: Python
Classifier: Programming Language :: Python :: 3
Classifier: Programming Language :: Python :: 3 :: Only
Classifier: Programming Language :: Python :: 3.8
Classifier: Programming Language :: Python :: 3.9
Classifier: Programming Language :: Python :: 3.10
Classifier: Programming Language :: Python :: 3.11
Classifier: Programming Language :: Python :: 3.12
Classifier: Topic :: Database
Classifier: Topic :: Software Development :: Libraries :: Python Modules
Requires-Python: >=3.8
License-File: LICENSE
Requires-Dist: requests>=2.25.0
Provides-Extra: observability
Requires-Dist: opentelemetry-api>=1.20.0; extra == "observability"
Requires-Dist: opentelemetry-sdk>=1.20.0; extra == "observability"
Requires-Dist: prometheus-client>=0.17.0; extra == "observability"
Requires-Dist: opentelemetry-exporter-otlp>=1.20.0; extra == "observability"
Requires-Dist: opentelemetry-exporter-jaeger>=1.20.0; extra == "observability"
Requires-Dist: opentelemetry-propagator-b3>=1.20.0; extra == "observability"
Requires-Dist: opentelemetry-instrumentation>=0.41b0; extra == "observability"
Dynamic: license-file
